{
  "season": 2018,
  "phase": "Regular Season",
  "team": "2 Mannschaft",
  "league": 19,
  "players": [
    {
      "rank": "1",
      "name": "Glauser Patrick",
      "position": "Stürmer",
      "games": 18,
      "goals": 28,
      "assists": 21,
      "points": 49,
      "pointsPerGame": 2.72,
      "penaltyMinutes": 36,
      "id": null,
      "jerseyNumber": null,
      "ageGroup": null
    },
    {
      "rank": "2",
      "name": "Vonarburg Marco",
      "position": "Stürmer",
      "games": 17,
      "goals": 10,
      "assists": 24,
      "points": 34,
      "pointsPerGame": 2,
      "penaltyMinutes": 0,
      "id": null,
      "jerseyNumber": null,
      "ageGroup": null
    },
    {
      "rank": "3",
      "name": "Kronenberg Severin",
      "position": "Verteidiger",
      "games": 17,
      "goals": 14,
      "assists": 11,
      "points": 25,
      "pointsPerGame": 1.47,
      "penaltyMinutes": 12,
      "id": null,
      "jerseyNumber": null,
      "ageGroup": null
    },
    {
      "rank": "4",
      "name": "Hänggi David",
      "position": "Verteidiger",
      "games": 17,
      "goals": 11,
      "assists": 12,
      "points": 23,
      "pointsPerGame": 1.35,
      "penaltyMinutes": 12,
      "id": null,
      "jerseyNumber": null,
      "ageGroup": null
    },
    {
      "rank": "5",
      "name": "Grüter Thomas",
      "position": "Stürmer",
      "games": 17,
      "goals": 10,
      "assists": 9,
      "points": 19,
      "pointsPerGame": 1.12,
      "penaltyMinutes": 42,
      "id": null,
      "jerseyNumber": null,
      "ageGroup": null
    },
    {
      "rank": "6",
      "name": "Faden Matthias",
      "position": "Stürmer",
      "games": 14,
      "goals": 9,
      "assists": 7,
      "points": 16,
      "pointsPerGame": 1.14,
      "penaltyMinutes": 14,
      "id": null,
      "jerseyNumber": null,
      "ageGroup": null
    },
    {
      "rank": "7",
      "name": "Hauenstein Christian",
      "position": "Stürmer",
      "games": 12,
      "goals": 10,
      "assists": 5,
      "points": 15,
      "pointsPerGame": 1.25,
      "penaltyMinutes": 6,
      "id": null,
      "jerseyNumber": null,
      "ageGroup": null
    },
    {
      "rank": "8",
      "name": "Limacher Patrik",
      "position": "Verteidiger",
      "games": 13,
      "goals": 5,
      "assists": 7,
      "points": 12,
      "pointsPerGame": 0.92,
      "penaltyMinutes": 4,
      "id": null,
      "jerseyNumber": null,
      "ageGroup": null
    },
    {
      "rank": "9",
      "name": "Wey Kilian",
      "position": "Stürmer",
      "games": 16,
      "goals": 5,
      "assists": 7,
      "points": 12,
      "pointsPerGame": 0.75,
      "penaltyMinutes": 8,
      "id": null,
      "jerseyNumber": null,
      "ageGroup": null
    },
    {
      "rank": "10",
      "name": "Troxler Daniel",
      "position": "Stürmer",
      "games": 11,
      "goals": 6,
      "assists": 4,
      "points": 10,
      "pointsPerGame": 0.91,
      "penaltyMinutes": 4,
      "id": null,
      "jerseyNumber": null,
      "ageGroup": null
    },
    {
      "rank": "11",
      "name": "Limacher Luca",
      "position": "Stürmer",
      "games": 10,
      "goals": 6,
      "assists": 3,
      "points": 9,
      "pointsPerGame": 0.9,
      "penaltyMinutes": 18,
      "id": null,
      "jerseyNumber": null,
      "ageGroup": null
    },
    {
      "rank": "12",
      "name": "Köppel Christian",
      "position": "Stürmer",
      "games": 16,
      "goals": 2,
      "assists": 5,
      "points": 7,
      "pointsPerGame": 0.44,
      "penaltyMinutes": 18,
      "id": null,
      "jerseyNumber": null,
      "ageGroup": null
    },
    {
      "rank": "13",
      "name": "Gassmann Pascal",
      "position": "Stürmer",
      "games": 15,
      "goals": 2,
      "assists": 5,
      "points": 7,
      "pointsPerGame": 0.47,
      "penaltyMinutes": 20,
      "id": null,
      "jerseyNumber": null,
      "ageGroup": null
    },
    {
      "rank": "14",
      "name": "Ineichen Daniel",
      "position": "Stürmer",
      "games": 13,
      "goals": 3,
      "assists": 3,
      "points": 6,
      "pointsPerGame": 0.46,
      "penaltyMinutes": 8,
      "id": null,
      "jerseyNumber": null,
      "ageGroup": null
    },
    {
      "rank": "15",
      "name": "Vonella Daniele",
      "position": "Stürmer",
      "games": 8,
      "goals": 2,
      "assists": 4,
      "points": 6,
      "pointsPerGame": 0.75,
      "penaltyMinutes": 16,
      "id": null,
      "jerseyNumber": null,
      "ageGroup": null
    },
    {
      "rank": "16",
      "name": "Schmid Daniel",
      "position": "Verteidiger",
      "games": 10,
      "goals": 2,
      "assists": 4,
      "points": 6,
      "pointsPerGame": 0.6,
      "penaltyMinutes": 30,
      "id": null,
      "jerseyNumber": null,
      "ageGroup": null
    },
    {
      "rank": "17",
      "name": "Hodel Flavio",
      "position": "Stürmer",
      "games": 4,
      "goals": 1,
      "assists": 2,
      "points": 3,
      "pointsPerGame": 0.75,
      "penaltyMinutes": 4,
      "id": null,
      "jerseyNumber": null,
      "ageGroup": null
    },
    {
      "rank": "18",
      "name": "Niederberger Lars",
      "position": "Verteidiger",
      "games": 2,
      "goals": 0,
      "assists": 2,
      "points": 2,
      "pointsPerGame": 1,
      "penaltyMinutes": 4,
      "id": null,
      "jerseyNumber": null,
      "ageGroup": null
    },
    {
      "rank": "19",
      "name": "Arnet Basil",
      "position": "Stürmer",
      "games": 1,
      "goals": 1,
      "assists": 0,
      "points": 1,
      "pointsPerGame": 1,
      "penaltyMinutes": 0,
      "id": null,
      "jerseyNumber": null,
      "ageGroup": null
    },
    {
      "rank": "20",
      "name": "Bürli Nicolas",
      "position": "Verteidiger",
      "games": 9,
      "goals": 0,
      "assists": 1,
      "points": 1,
      "pointsPerGame": 0.11,
      "penaltyMinutes": 20,
      "id": null,
      "jerseyNumber": null,
      "ageGroup": null
    },
    {
      "rank": "21",
      "name": "Krauer Julian",
      "position": "Stürmer",
      "games": 2,
      "goals": 0,
      "assists": 0,
      "points": 0,
      "pointsPerGame": 0,
      "penaltyMinutes": 0,
      "id": null,
      "jerseyNumber": null,
      "ageGroup": null
    }
  ]
}